murano_pkg_check-0.2.0.dist-info/DESCRIPTION.rst
murano_pkg_check-0.2.0.dist-info/METADATA
murano_pkg_check-0.2.0.dist-info/RECORD
murano_pkg_check-0.2.0.dist-info/WHEEL
murano_pkg_check-0.2.0.dist-info/entry_points.txt
murano_pkg_check-0.2.0.dist-info/metadata.json
murano_pkg_check-0.2.0.dist-info/pbr.json
murano_pkg_check-0.2.0.dist-info/top_level.txt
muranopkgcheck/__init__.py
muranopkgcheck/consts.py
muranopkgcheck/error.py
muranopkgcheck/i18n.py
muranopkgcheck/log.py
muranopkgcheck/manager.py
muranopkgcheck/pkg_loader.py
muranopkgcheck/plugin.py
muranopkgcheck/yaml_loader.py
muranopkgcheck/checkers/__init__.py
muranopkgcheck/checkers/code_structure.py
muranopkgcheck/checkers/yaql_checker.py
muranopkgcheck/cmd/__init__.py
muranopkgcheck/cmd/run.py
muranopkgcheck/tests/__init__.py
muranopkgcheck/tests/base.py
muranopkgcheck/tests/test_code_structure_checker.py
muranopkgcheck/tests/test_error.py
muranopkgcheck/tests/test_log.py
muranopkgcheck/tests/test_manager.py
muranopkgcheck/tests/test_manifest_validator.py
muranopkgcheck/tests/test_muranopl_validator.py
muranopkgcheck/tests/test_package.py
muranopkgcheck/tests/test_pkg_loader.py
muranopkgcheck/tests/test_plugin.py
muranopkgcheck/tests/test_ui_validator.py
muranopkgcheck/tests/test_validator_helpers.py
muranopkgcheck/tests/test_yaml_validator.py
muranopkgcheck/tests/functional/__init__.py
muranopkgcheck/tests/functional/test_cases.py
muranopkgcheck/tests/functional/cases/case.yaml
muranopkgcheck/validators/__init__.py
muranopkgcheck/validators/base.py
muranopkgcheck/validators/manifest.py
muranopkgcheck/validators/muranopl.py
muranopkgcheck/validators/package.py
muranopkgcheck/validators/ui.py
