Metadata-Version: 2.0
Name: murano-pkg-check
Version: 0.2.0
Summary: Murano package validator tool
Home-page: http://docs.openstack.org/developer/murano/
Author: OpenStack
Author-email: openstack-dev@lists.openstack.org
License: UNKNOWN
Platform: UNKNOWN
Classifier: Environment :: OpenStack
Classifier: Intended Audience :: Information Technology
Classifier: Intended Audience :: Developers
Classifier: License :: OSI Approved :: Apache Software License
Classifier: Operating System :: POSIX :: Linux
Classifier: Programming Language :: Python
Classifier: Programming Language :: Python :: 2
Classifier: Programming Language :: Python :: 2.7
Classifier: Programming Language :: Python :: 3
Classifier: Programming Language :: Python :: 3.4
Classifier: Programming Language :: Python :: 3.5
Requires-Dist: pbr (>=1.6)
Requires-Dist: PyYAML (>=3.10.0)
Requires-Dist: yaql (>=1.1.0)
Requires-Dist: six (>=1.9.0)
Requires-Dist: stevedore (>=1.16.0)
Requires-Dist: semantic-version (>=2.3.1)
Requires-Dist: oslo.i18n (>=2.1.0)
